pysinewave/__init__.py
pysinewave/__main__.py
pysinewave/sinewave.py
pysinewave/sinewave_generator.py
pysinewave/utilities.py
pysinewave-0.0.6.dist-info/LICENSE
pysinewave-0.0.6.dist-info/METADATA
pysinewave-0.0.6.dist-info/WHEEL
pysinewave-0.0.6.dist-info/top_level.txt
pysinewave-0.0.6.dist-info/RECORD
