Metadata-Version: 2.1
Name: pysinewave
Version: 0.0.6
Summary: Generate and play sine waves in real time, that can make smooth, continuous transitions in pitch and volume.
Home-page: https://github.com/daviddavini/continuous-sine-wave
Author: David Davini
Author-email: daviddavini@ucla.com
License: UNKNOWN
Platform: UNKNOWN
Classifier: Programming Language :: Python :: 3
Classifier: License :: OSI Approved :: MIT License
Classifier: Operating System :: OS Independent
Requires-Python: >=3.6
Requires-Dist: numpy
Requires-Dist: sounddevice
